intertidal/__init__.py
intertidal/composites.py
intertidal/elevation.py
intertidal/exposure.py
intertidal/extents.py
intertidal/io.py
intertidal/mosaics.py
intertidal/tidal_bias_offset.py
intertidal/utils.py
intertidal/validation.py
dea_intertidal-2.4.0.dist-info/METADATA
dea_intertidal-2.4.0.dist-info/WHEEL
dea_intertidal-2.4.0.dist-info/entry_points.txt
dea_intertidal-2.4.0.dist-info/licenses/LICENSE
dea_intertidal-2.4.0.dist-info/RECORD
