Metadata-Version: 2.4
Name: dea-intertidal
Version: 2.4.0
Summary: Remote sensing tools for high-resolution mapping of the intertidal zone
Project-URL: Homepage, https://github.com/GeoscienceAustralia/eo-tides
Project-URL: Repository, https://github.com/GeoscienceAustralia/eo-tides
Author: Robbi Bishop-Taylor, Claire Phillips, Vanessa Newey, Stephen Sagar
Author-email: Robbi.BishopTaylor@ga.gov.au
License-File: LICENSE
Keywords: coastal,coastal analysis,earth observation,exposure,intertidal,oceanography,remote sensing,satellite data,tide modelling
Classifier: Development Status :: 3 - Alpha
Classifier: Intended Audience :: Science/Research
Classifier: License :: OSI Approved :: Apache Software License
Classifier: Programming Language :: Python :: 3.10
Classifier: Programming Language :: Python :: 3.11
Classifier: Programming Language :: Python :: 3.12
Classifier: Programming Language :: Python :: 3.13
Classifier: Topic :: Scientific/Engineering
Classifier: Topic :: Scientific/Engineering :: GIS
Classifier: Topic :: Scientific/Engineering :: Image Processing
Classifier: Topic :: Scientific/Engineering :: Oceanography
Classifier: Topic :: Scientific/Engineering :: Visualization
Requires-Python: <4.0,>=3.10
Requires-Dist: bottleneck>=1.4.2
Requires-Dist: click>=8.1.7
Requires-Dist: cmocean>=4.0.0
Requires-Dist: dea-tools>=0.4.7
Requires-Dist: eo-tides>=0.10.0
Requires-Dist: folium>=0.16.0
Requires-Dist: geopandas>=0.14.4
Requires-Dist: matplotlib>=3.9.2
Requires-Dist: numpy>=1.26.4
Requires-Dist: odc-algo>=1.1.1
Requires-Dist: odc-geo>=0.4.8
Requires-Dist: pandas>=2.2.3
Requires-Dist: pyogrio>=0.10.0
Requires-Dist: pytz>=2024.1
Requires-Dist: rasterio>=1.4.1
Requires-Dist: s3fs>=2024.9.0
Requires-Dist: scikit-image>=0.24.0
Requires-Dist: scipy>=1.14.1
Requires-Dist: seaborn>=0.13.2
Requires-Dist: sunriset>=1.0
Requires-Dist: tqdm>=4.66.5
Requires-Dist: xarray-spatial>=0.4.0
Requires-Dist: xarray>=2024.9.0
Provides-Extra: datacube
Requires-Dist: datacube[performance,postgres,s3]>=1.8.19; extra == 'datacube'
Requires-Dist: eodatasets3>=0.30.9; extra == 'datacube'
Requires-Dist: odc-ui>=0.2.1; extra == 'datacube'
